{
  "Vlakové nádraží": {
    "lat": 49.847689,
    "lng": 18.42574
  },
  "Kostel Narození Panny Marie": {
    "lat": 49.84616,
    "lng": 18.429968
  },
  "Zámecký park a bývalý zámek": {
    "lat": 49.846779,
    "lng": 18.431491
  },
  "Dělnický dům": {
    "lat": 49.846781,
    "lng": 18.434521
  },
  "Polské gymnázium Juliusze Słowackiego": {
    "lat": 49.851024,
    "lng": 18.435174
  },
  "Židovský templ": {
    "lat": 49.846341,
    "lng": 18.440791
  },
  "Evangelický kostel": {
    "lat": 49.846299,
    "lng": 18.439748
  },
  "České gymnázium": {
    "lat": 49.84666,
    "lng": 18.43774
  },
  "Věčný oheň": {
    "lat": 49.846369,
    "lng": 18.434185
  },
  "Husův dům": {
    "lat": 49.844062,
    "lng": 18.434839
  },
  "Pomník padlým za Těšínsko": {
    "lat": 49.840596,
    "lng": 18.424796
  },
  "Důl Žofie": {
    "lat": 49.845525,
    "lng": 18.418808
  }
}
